pytescript_thanhnghi/__init__.py
pytescript_thanhnghi/example.py
pytescript-0.0.0.dist-info/LICENSE
pytescript-0.0.0.dist-info/METADATA
pytescript-0.0.0.dist-info/WHEEL
pytescript-0.0.0.dist-info/top_level.txt
pytescript-0.0.0.dist-info/RECORD
