Metadata-Version: 2.1
Name: pytescript
Version: 0.0.0
Summary: A library that converts between python and typescript interfaces
Author-email: Nguyen Thanh Nghi <thanhnghic4@gmail.com>
License: MIT
Project-URL: repository, https://github.com/thanhnghic4/Pypescript
Project-URL: homepage, https://github.com/thanhnghic4/Pypescript
Project-URL: documentation, https://github.com/thanhnghic4/Pypescript
Keywords: python,typescript,interfaces,yaml,dataclass,share
Classifier: License :: OSI Approved :: MIT License
Classifier: Operating System :: OS Independent
Classifier: Programming Language :: Python
Classifier: Programming Language :: Python :: 3 :: Only
Classifier: Programming Language :: Python :: 3.7
Classifier: Programming Language :: Python :: 3.8
Classifier: Programming Language :: Python :: 3.9
Classifier: Programming Language :: Python :: 3.10
Classifier: Typing :: Typed
Requires-Python: >=3.7
License-File: LICENSE
